{
  "__inputs": [
    {
      "name": "DS_PROMETHEUS",
      "label": "prometheus",
      "description": "",
      "type": "datasource",
      "pluginId": "prometheus",
      "pluginName": "Prometheus"
    }
  ],
  "__requires": [
    {
      "type": "grafana",
      "id": "grafana",
      "name": "Grafana",
      "version": "4.6.2"
    },
    {
      "type": "panel",
      "id": "graph",
      "name": "Graph",
      "version": ""
    },
    {
      "type": "datasource",
      "id": "prometheus",
      "name": "Prometheus",
      "version": "1.0.0"
    }
  ],
  "annotations": {
    "list": [
      {
        "builtIn": 1,
        "datasource": "-- Grafana --",
        "enable": true,
        "hide": true,
        "iconColor": "rgba(0, 211, 255, 1)",
        "name": "Annotations & Alerts",
        "type": "dashboard"
      }
    ]
  },
  "description": "Hummingbird stats",
  "editable": true,
  "gnetId": 240,
  "graphTooltip": 0,
  "hideControls": false,
  "id": null,
  "links": [],
  "refresh": false,
  "rows": [
    {
      "collapse": false,
      "height": 249,
      "panels": [
        {
          "aliasColors": {},
          "bars": false,
          "dashLength": 10,
          "dashes": false,
          "datasource": "${DS_PROMETHEUS}",
          "editable": true,
          "error": false,
          "fill": 1,
          "grid": {},
          "id": 1,
          "legend": {
            "avg": false,
            "current": false,
            "max": false,
            "min": false,
            "show": true,
            "total": false,
            "values": false
          },
          "lines": true,
          "linewidth": 2,
          "links": [],
          "nullPointMode": "connected",
          "percentage": false,
          "pointradius": 5,
          "points": false,
          "renderer": "flot",
          "seriesOverrides": [
            {
              "alias": "resident",
              "yaxis": 2
            }
          ],
          "spaceLength": 10,
          "span": 6,
          "stack": false,
          "steppedLine": false,
          "targets": [
            {
              "expr": "process_resident_memory_bytes{job=~\"$job\"}",
              "format": "time_series",
              "intervalFactor": 2,
              "legendFormat": "resident",
              "metric": "process_resident_memory_bytes",
              "refId": "A",
              "step": 4
            },
            {
              "expr": "process_virtual_memory_bytes{job=~\"$job\"}",
              "format": "time_series",
              "intervalFactor": 2,
              "legendFormat": "virtual",
              "metric": "process_virtual_memory_bytes",
              "refId": "B",
              "step": 4
            }
          ],
          "thresholds": [],
          "timeFrom": null,
          "timeShift": null,
          "title": "process memory",
          "tooltip": {
            "msResolution": false,
            "shared": true,
            "sort": 0,
            "value_type": "cumulative"
          },
          "type": "graph",
          "xaxis": {
            "buckets": null,
            "mode": "time",
            "name": null,
            "show": true,
            "values": []
          },
          "yaxes": [
            {
              "format": "bytes",
              "label": null,
              "logBase": 1,
              "max": null,
              "min": null,
              "show": true
            },
            {
              "format": "short",
              "label": null,
              "logBase": 1,
              "max": null,
              "min": null,
              "show": true
            }
          ]
        },
        {
          "aliasColors": {},
          "bars": false,
          "dashLength": 10,
          "dashes": false,
          "datasource": "${DS_PROMETHEUS}",
          "editable": true,
          "error": false,
          "fill": 1,
          "grid": {},
          "id": 4,
          "legend": {
            "avg": false,
            "current": false,
            "max": false,
            "min": false,
            "show": true,
            "total": false,
            "values": false
          },
          "lines": true,
          "linewidth": 2,
          "links": [],
          "nullPointMode": "connected",
          "percentage": false,
          "pointradius": 5,
          "points": false,
          "renderer": "flot",
          "seriesOverrides": [
            {
              "alias": "resident",
              "yaxis": 1
            }
          ],
          "spaceLength": 10,
          "span": 6,
          "stack": false,
          "steppedLine": false,
          "targets": [
            {
              "expr": "rate(process_resident_memory_bytes{job=~\"$job\"}[$interval])",
              "format": "time_series",
              "interval": "",
              "intervalFactor": 2,
              "legendFormat": "resident",
              "metric": "process_resident_memory_bytes",
              "refId": "A",
              "step": 4
            },
            {
              "expr": "deriv(process_virtual_memory_bytes{job=~\"$job\"}[$interval])",
              "format": "time_series",
              "intervalFactor": 2,
              "legendFormat": "virtual",
              "metric": "process_virtual_memory_bytes",
              "refId": "B",
              "step": 4
            }
          ],
          "thresholds": [],
          "timeFrom": null,
          "timeShift": null,
          "title": "process memory deriv",
          "tooltip": {
            "msResolution": false,
            "shared": true,
            "sort": 0,
            "value_type": "cumulative"
          },
          "type": "graph",
          "xaxis": {
            "buckets": null,
            "mode": "time",
            "name": null,
            "show": true,
            "values": []
          },
          "yaxes": [
            {
              "format": "bytes",
              "label": null,
              "logBase": 1,
              "max": null,
              "min": null,
              "show": true
            },
            {
              "format": "short",
              "label": null,
              "logBase": 1,
              "max": null,
              "min": null,
              "show": true
            }
          ]
        },
        {
          "aliasColors": {},
          "bars": false,
          "dashLength": 10,
          "dashes": false,
          "datasource": "${DS_PROMETHEUS}",
          "editable": true,
          "error": false,
          "fill": 1,
          "grid": {},
          "id": 2,
          "legend": {
            "avg": false,
            "current": false,
            "max": false,
            "min": false,
            "show": true,
            "total": false,
            "values": false
          },
          "lines": true,
          "linewidth": 2,
          "links": [],
          "nullPointMode": "connected",
          "percentage": false,
          "pointradius": 5,
          "points": false,
          "renderer": "flot",
          "seriesOverrides": [
            {
              "alias": "alloc rate",
              "yaxis": 2
            }
          ],
          "spaceLength": 10,
          "span": 6,
          "stack": false,
          "steppedLine": false,
          "targets": [
            {
              "expr": "go_memstats_alloc_bytes{job=\"$job\"}",
              "format": "time_series",
              "intervalFactor": 2,
              "legendFormat": "bytes allocated",
              "metric": "go_memstats_alloc_bytes",
              "refId": "A",
              "step": 4
            },
            {
              "expr": "go_memstats_stack_inuse_bytes{job=\"$job\"}",
              "format": "time_series",
              "intervalFactor": 2,
              "legendFormat": "stack inuse",
              "metric": "go_memstats_stack_inuse_bytes",
              "refId": "C",
              "step": 4
            },
            {
              "expr": "go_memstats_heap_inuse_bytes{job=\"$job\"}",
              "format": "time_series",
              "hide": false,
              "intervalFactor": 2,
              "legendFormat": "heap inuse",
              "metric": "go_memstats_heap_inuse_bytes",
              "refId": "D",
              "step": 4
            },
            {
              "expr": "go_memstats_buck_hash_sys_bytes{job=\"$job\"}",
              "format": "time_series",
              "intervalFactor": 2,
              "legendFormat": "bytes bucket hash",
              "refId": "E"
            }
          ],
          "thresholds": [],
          "timeFrom": null,
          "timeShift": null,
          "title": "go memstats",
          "tooltip": {
            "msResolution": false,
            "shared": true,
            "sort": 0,
            "value_type": "cumulative"
          },
          "type": "graph",
          "xaxis": {
            "buckets": null,
            "mode": "time",
            "name": null,
            "show": true,
            "values": []
          },
          "yaxes": [
            {
              "format": "bytes",
              "label": null,
              "logBase": 1,
              "max": null,
              "min": null,
              "show": true
            },
            {
              "format": "Bps",
              "label": null,
              "logBase": 1,
              "max": null,
              "min": null,
              "show": true
            }
          ]
        },
        {
          "aliasColors": {},
          "bars": false,
          "dashLength": 10,
          "dashes": false,
          "datasource": "${DS_PROMETHEUS}",
          "editable": true,
          "error": false,
          "fill": 1,
          "grid": {},
          "id": 5,
          "legend": {
            "avg": false,
            "current": false,
            "max": false,
            "min": false,
            "show": true,
            "total": false,
            "values": false
          },
          "lines": true,
          "linewidth": 2,
          "links": [],
          "nullPointMode": "connected",
          "percentage": false,
          "pointradius": 5,
          "points": false,
          "renderer": "flot",
          "seriesOverrides": [
            {
              "alias": "alloc rate",
              "yaxis": 2
            }
          ],
          "spaceLength": 10,
          "span": 6,
          "stack": false,
          "steppedLine": false,
          "targets": [
            {
              "expr": "deriv(go_memstats_alloc_bytes{job=\"$job\"}[$interval])",
              "format": "time_series",
              "intervalFactor": 2,
              "legendFormat": "bytes allocated",
              "metric": "go_memstats_alloc_bytes",
              "refId": "A",
              "step": 4
            },
            {
              "expr": "rate(go_memstats_alloc_bytes_total{job=\"$job\"}[$interval])",
              "format": "time_series",
              "intervalFactor": 2,
              "legendFormat": "alloc rate",
              "metric": "go_memstats_alloc_bytes_total",
              "refId": "B",
              "step": 4
            },
            {
              "expr": "deriv(go_memstats_stack_inuse_bytes{job=\"$job\"}[$interval])",
              "format": "time_series",
              "intervalFactor": 2,
              "legendFormat": "stack inuse",
              "metric": "go_memstats_stack_inuse_bytes",
              "refId": "C",
              "step": 4
            },
            {
              "expr": "deriv(go_memstats_heap_inuse_bytes{job=\"$job\"}[$interval])",
              "format": "time_series",
              "hide": false,
              "intervalFactor": 2,
              "legendFormat": "heap inuse",
              "metric": "go_memstats_heap_inuse_bytes",
              "refId": "D",
              "step": 4
            }
          ],
          "thresholds": [],
          "timeFrom": null,
          "timeShift": null,
          "title": "go memstats deriv",
          "tooltip": {
            "msResolution": false,
            "shared": true,
            "sort": 0,
            "value_type": "cumulative"
          },
          "type": "graph",
          "xaxis": {
            "buckets": null,
            "mode": "time",
            "name": null,
            "show": true,
            "values": []
          },
          "yaxes": [
            {
              "format": "bytes",
              "label": null,
              "logBase": 1,
              "max": null,
              "min": null,
              "show": true
            },
            {
              "format": "Bps",
              "label": null,
              "logBase": 1,
              "max": null,
              "min": null,
              "show": true
            }
          ]
        }
      ],
      "repeat": null,
      "repeatIteration": null,
      "repeatRowId": null,
      "showTitle": false,
      "title": "Row",
      "titleSize": "h6"
    },
    {
      "collapse": false,
      "height": "250px",
      "panels": [
        {
          "aliasColors": {},
          "bars": false,
          "dashLength": 10,
          "dashes": false,
          "datasource": "${DS_PROMETHEUS}",
          "editable": true,
          "error": false,
          "fill": 1,
          "grid": {},
          "id": 3,
          "legend": {
            "avg": false,
            "current": false,
            "max": false,
            "min": false,
            "show": true,
            "total": false,
            "values": false
          },
          "lines": true,
          "linewidth": 2,
          "links": [],
          "nullPointMode": "connected",
          "percentage": false,
          "pointradius": 5,
          "points": false,
          "renderer": "flot",
          "seriesOverrides": [],
          "spaceLength": 10,
          "span": 6,
          "stack": false,
          "steppedLine": false,
          "targets": [
            {
              "expr": "process_open_fds{job=\"$job\"}",
              "format": "time_series",
              "intervalFactor": 2,
              "legendFormat": "{{job}}",
              "metric": "process_open_fds",
              "refId": "A",
              "step": 4
            }
          ],
          "thresholds": [],
          "timeFrom": null,
          "timeShift": null,
          "title": "open fds",
          "tooltip": {
            "msResolution": false,
            "shared": true,
            "sort": 0,
            "value_type": "cumulative"
          },
          "type": "graph",
          "xaxis": {
            "buckets": null,
            "mode": "time",
            "name": null,
            "show": true,
            "values": []
          },
          "yaxes": [
            {
              "format": "short",
              "label": null,
              "logBase": 1,
              "max": null,
              "min": null,
              "show": true
            },
            {
              "format": "short",
              "label": null,
              "logBase": 1,
              "max": null,
              "min": null,
              "show": true
            }
          ]
        },
        {
          "aliasColors": {},
          "bars": false,
          "dashLength": 10,
          "dashes": false,
          "datasource": "${DS_PROMETHEUS}",
          "editable": true,
          "error": false,
          "fill": 1,
          "grid": {},
          "id": 6,
          "legend": {
            "avg": false,
            "current": false,
            "max": false,
            "min": false,
            "show": true,
            "total": false,
            "values": false
          },
          "lines": true,
          "linewidth": 2,
          "links": [],
          "nullPointMode": "connected",
          "percentage": false,
          "pointradius": 5,
          "points": false,
          "renderer": "flot",
          "seriesOverrides": [],
          "spaceLength": 10,
          "span": 6,
          "stack": false,
          "steppedLine": false,
          "targets": [
            {
              "expr": "deriv(process_open_fds{job=\"$job\"}[$interval])",
              "format": "time_series",
              "intervalFactor": 2,
              "metric": "process_open_fds",
              "refId": "A",
              "step": 4
            }
          ],
          "thresholds": [],
          "timeFrom": null,
          "timeShift": null,
          "title": "open fds deriv",
          "tooltip": {
            "msResolution": false,
            "shared": true,
            "sort": 0,
            "value_type": "cumulative"
          },
          "type": "graph",
          "xaxis": {
            "buckets": null,
            "mode": "time",
            "name": null,
            "show": true,
            "values": []
          },
          "yaxes": [
            {
              "format": "short",
              "label": null,
              "logBase": 1,
              "max": null,
              "min": null,
              "show": true
            },
            {
              "format": "short",
              "label": null,
              "logBase": 1,
              "max": null,
              "min": null,
              "show": true
            }
          ]
        }
      ],
      "repeat": null,
      "repeatIteration": null,
      "repeatRowId": null,
      "showTitle": false,
      "title": "New row",
      "titleSize": "h6"
    },
    {
      "collapse": false,
      "height": "250px",
      "panels": [
        {
          "aliasColors": {},
          "bars": false,
          "dashLength": 10,
          "dashes": false,
          "datasource": "${DS_PROMETHEUS}",
          "editable": true,
          "error": false,
          "fill": 1,
          "grid": {},
          "id": 7,
          "legend": {
            "avg": false,
            "current": false,
            "max": false,
            "min": false,
            "show": true,
            "total": false,
            "values": false
          },
          "lines": true,
          "linewidth": 2,
          "links": [],
          "nullPointMode": "null",
          "percentage": false,
          "pointradius": 5,
          "points": false,
          "renderer": "flot",
          "seriesOverrides": [],
          "spaceLength": 10,
          "span": 6,
          "stack": false,
          "steppedLine": false,
          "targets": [
            {
              "expr": "go_goroutines{job=\"$job\"}",
              "format": "time_series",
              "interval": "",
              "intervalFactor": 2,
              "legendFormat": "{{job}}",
              "metric": "go_goroutines",
              "refId": "A",
              "step": 4
            }
          ],
          "thresholds": [],
          "timeFrom": null,
          "timeShift": null,
          "title": "Goroutines",
          "tooltip": {
            "msResolution": false,
            "shared": true,
            "sort": 0,
            "value_type": "cumulative"
          },
          "type": "graph",
          "xaxis": {
            "buckets": null,
            "mode": "time",
            "name": null,
            "show": true,
            "values": []
          },
          "yaxes": [
            {
              "format": "short",
              "label": null,
              "logBase": 1,
              "max": null,
              "min": null,
              "show": true
            },
            {
              "format": "short",
              "label": null,
              "logBase": 1,
              "max": null,
              "min": null,
              "show": true
            }
          ]
        },
        {
          "aliasColors": {},
          "bars": false,
          "dashLength": 10,
          "dashes": false,
          "datasource": "${DS_PROMETHEUS}",
          "editable": true,
          "error": false,
          "fill": 1,
          "grid": {},
          "id": 8,
          "legend": {
            "avg": false,
            "current": false,
            "max": false,
            "min": false,
            "show": true,
            "total": false,
            "values": false
          },
          "lines": true,
          "linewidth": 2,
          "links": [],
          "nullPointMode": "connected",
          "percentage": false,
          "pointradius": 5,
          "points": false,
          "renderer": "flot",
          "seriesOverrides": [],
          "spaceLength": 10,
          "span": 6,
          "stack": false,
          "steppedLine": false,
          "targets": [
            {
              "expr": "go_gc_duration_seconds{job=\"$job\"}",
              "format": "time_series",
              "intervalFactor": 2,
              "legendFormat": "{{quantile}}",
              "metric": "go_gc_duration_seconds",
              "refId": "A",
              "step": 4
            }
          ],
          "thresholds": [],
          "timeFrom": null,
          "timeShift": null,
          "title": "GC duration quantiles",
          "tooltip": {
            "msResolution": false,
            "shared": true,
            "sort": 0,
            "value_type": "cumulative"
          },
          "type": "graph",
          "xaxis": {
            "buckets": null,
            "mode": "time",
            "name": null,
            "show": true,
            "values": []
          },
          "yaxes": [
            {
              "format": "s",
              "label": null,
              "logBase": 1,
              "max": null,
              "min": null,
              "show": true
            },
            {
              "format": "short",
              "label": null,
              "logBase": 1,
              "max": null,
              "min": null,
              "show": true
            }
          ]
        }
      ],
      "repeat": null,
      "repeatIteration": null,
      "repeatRowId": null,
      "showTitle": false,
      "title": "New row",
      "titleSize": "h6"
    },
    {
      "collapse": false,
      "height": 183,
      "panels": [
        {
          "aliasColors": {},
          "bars": false,
          "dashLength": 10,
          "dashes": false,
          "datasource": "${DS_PROMETHEUS}",
          "fill": 1,
          "id": 9,
          "legend": {
            "avg": false,
            "current": false,
            "max": false,
            "min": false,
            "show": true,
            "total": false,
            "values": false
          },
          "lines": true,
          "linewidth": 1,
          "links": [],
          "nullPointMode": "null",
          "percentage": false,
          "pointradius": 5,
          "points": false,
          "renderer": "flot",
          "seriesOverrides": [],
          "spaceLength": 10,
          "span": 12,
          "stack": false,
          "steppedLine": false,
          "targets": [
            {
              "expr": "rate(hb_proxy_201_responses{job=\"$job\"}[30s])",
              "format": "time_series",
              "intervalFactor": 2,
              "legendFormat": "201 response",
              "refId": "A"
            },
            {
              "expr": "rate(hb_proxy_200_responses{job=\"$job\"}[30s])",
              "format": "time_series",
              "intervalFactor": 2,
              "legendFormat": "200 response",
              "refId": "B"
            },
            {
              "expr": "rate(hb_proxy_204_responses{job=\"$job\"}[30s])",
              "format": "time_series",
              "intervalFactor": 2,
              "legendFormat": "204 response",
              "refId": "C"
            },
            {
              "expr": "rate(hb_proxy_412_responses{job=\"$job\"}[30s])",
              "format": "time_series",
              "intervalFactor": 2,
              "refId": "D"
            }
          ],
          "thresholds": [],
          "timeFrom": null,
          "timeShift": null,
          "title": "Proxy Responses",
          "tooltip": {
            "shared": true,
            "sort": 0,
            "value_type": "individual"
          },
          "type": "graph",
          "xaxis": {
            "buckets": null,
            "mode": "time",
            "name": null,
            "show": true,
            "values": []
          },
          "yaxes": [
            {
              "format": "short",
              "label": null,
              "logBase": 1,
              "max": null,
              "min": null,
              "show": true
            },
            {
              "format": "short",
              "label": null,
              "logBase": 1,
              "max": null,
              "min": null,
              "show": true
            }
          ]
        }
      ],
      "repeat": null,
      "repeatIteration": null,
      "repeatRowId": null,
      "showTitle": false,
      "title": "Dashboard Row",
      "titleSize": "h6"
    },
    {
      "collapse": false,
      "height": 250,
      "panels": [
        {
          "aliasColors": {},
          "bars": false,
          "dashLength": 10,
          "dashes": false,
          "datasource": "${DS_PROMETHEUS}",
          "fill": 1,
          "id": 10,
          "legend": {
            "avg": false,
            "current": false,
            "max": false,
            "min": false,
            "show": true,
            "total": false,
            "values": false
          },
          "lines": true,
          "linewidth": 1,
          "links": [],
          "nullPointMode": "null",
          "percentage": false,
          "pointradius": 5,
          "points": false,
          "renderer": "flot",
          "seriesOverrides": [],
          "spaceLength": 10,
          "span": 12,
          "stack": false,
          "steppedLine": false,
          "targets": [
            {
              "expr": "rate(hb_proxy_GET_requests{job=\"$job\"}[30s])",
              "format": "time_series",
              "intervalFactor": 2,
              "legendFormat": "proxy GET",
              "refId": "A"
            },
            {
              "expr": "rate(hb_proxy_PUT_requests{job=\"$job\"}[30s])",
              "format": "time_series",
              "intervalFactor": 2,
              "legendFormat": "proxy PUT",
              "refId": "B"
            },
            {
              "expr": "rate(hb_proxy_HEAD_requests{job=\"$job\"}[30s])",
              "format": "time_series",
              "intervalFactor": 2,
              "legendFormat": "proxy HEAD",
              "refId": "C"
            },
            {
              "expr": "rate(hb_proxy_bulk_delete_requests{job=\"$job\"}[30s])",
              "format": "time_series",
              "intervalFactor": 2,
              "legendFormat": "proxy BULK DELETE",
              "refId": "D"
            },
            {
              "expr": "rate(hb_proxy_bulk_put_requests{job=\"$job\"}[30s])",
              "format": "time_series",
              "intervalFactor": 2,
              "legendFormat": "proxy BULK PUT",
              "refId": "E"
            },
            {
              "expr": "rate(hb_proxy_requests{job=\"$job\"}[30s])",
              "format": "time_series",
              "intervalFactor": 2,
              "legendFormat": "proxy total REQ",
              "refId": "F"
            },
            {
              "expr": "rate(hb_proxy_recovers{job=\"$job\"}[30s])",
              "format": "time_series",
              "intervalFactor": 2,
              "legendFormat": "proxy recover",
              "refId": "G"
            },
            {
              "expr": "rate(hb_proxy_slo_GET_requests{job=\"$job\"}[30s])",
              "format": "time_series",
              "intervalFactor": 2,
              "legendFormat": "SLO GET",
              "refId": "H"
            },
            {
              "expr": "rate(hb_proxy_slo_DELETE_requests{job=\"$job\"}[30s])",
              "format": "time_series",
              "intervalFactor": 2,
              "legendFormat": "SLO DELETE",
              "refId": "I"
            },
            {
              "expr": "rate(hb_proxy_slo_PUT_requests{job=\"$job\"}[30s])",
              "format": "time_series",
              "intervalFactor": 2,
              "legendFormat": "SLO PUT",
              "refId": "J"
            },
            {
              "expr": "rate(hb_proxy_formpost_requests{job=\"$job\"}[30s])",
              "format": "time_series",
              "intervalFactor": 2,
              "legendFormat": "FORM POST ",
              "refId": "K"
            },
            {
              "expr": "rate(hb_proxy_dlo_GET_requests{job=\"$job\"}[30s])",
              "format": "time_series",
              "intervalFactor": 2,
              "legendFormat": "DLO GET",
              "refId": "L"
            },
            {
              "expr": "rate(hb_proxy_tempurl_requests{job=\"$job\"}[30s])",
              "format": "time_series",
              "intervalFactor": 2,
              "legendFormat": "tempurl",
              "refId": "M"
            },
            {
              "expr": "rate(hb_proxy_staticweb_requests{job=\"$job\"}[30s])",
              "format": "time_series",
              "intervalFactor": 2,
              "legendFormat": "staticweb ",
              "refId": "N"
            }
          ],
          "thresholds": [],
          "timeFrom": null,
          "timeShift": null,
          "title": "Proxy Requests",
          "tooltip": {
            "shared": true,
            "sort": 0,
            "value_type": "individual"
          },
          "type": "graph",
          "xaxis": {
            "buckets": null,
            "mode": "time",
            "name": null,
            "show": true,
            "values": []
          },
          "yaxes": [
            {
              "format": "short",
              "label": null,
              "logBase": 1,
              "max": null,
              "min": null,
              "show": true
            },
            {
              "format": "short",
              "label": null,
              "logBase": 1,
              "max": null,
              "min": null,
              "show": true
            }
          ]
        }
      ],
      "repeat": null,
      "repeatIteration": null,
      "repeatRowId": null,
      "showTitle": false,
      "title": "Dashboard Row",
      "titleSize": "h6"
    },
    {
      "collapse": false,
      "height": 310,
      "panels": [
        {
          "aliasColors": {},
          "bars": false,
          "dashLength": 10,
          "dashes": false,
          "datasource": "${DS_PROMETHEUS}",
          "fill": 1,
          "id": 11,
          "legend": {
            "avg": false,
            "current": false,
            "max": false,
            "min": false,
            "show": true,
            "total": false,
            "values": false
          },
          "lines": true,
          "linewidth": 1,
          "links": [],
          "nullPointMode": "null",
          "percentage": false,
          "pointradius": 5,
          "points": false,
          "renderer": "flot",
          "seriesOverrides": [],
          "spaceLength": 10,
          "span": 6,
          "stack": false,
          "steppedLine": false,
          "targets": [
            {
              "expr": "rate(hb_account_200_responses{job=\"$job\"}[30s])",
              "format": "time_series",
              "intervalFactor": 2,
              "legendFormat": "200 response",
              "refId": "A"
            },
            {
              "expr": "rate(hb_account_201_responses{job=\"$job\"}[30s])",
              "format": "time_series",
              "intervalFactor": 2,
              "legendFormat": "201 response",
              "refId": "B"
            },
            {
              "expr": "rate(hb_account_204_responses{job=\"$job\"}[30s])",
              "format": "time_series",
              "intervalFactor": 2,
              "legendFormat": "204 response",
              "refId": "C"
            },
            {
              "expr": "rate(hb_account_400_responses{job=\"$job\"}[30s])",
              "format": "time_series",
              "intervalFactor": 2,
              "legendFormat": "400 response",
              "refId": "D"
            },
            {
              "expr": "rate(hb_account_404_responses{job=\"$job\"}[30s])",
              "format": "time_series",
              "intervalFactor": 2,
              "legendFormat": "404 response",
              "refId": "E"
            }
          ],
          "thresholds": [],
          "timeFrom": null,
          "timeShift": null,
          "title": "Account Response",
          "tooltip": {
            "shared": true,
            "sort": 0,
            "value_type": "individual"
          },
          "type": "graph",
          "xaxis": {
            "buckets": null,
            "mode": "time",
            "name": null,
            "show": true,
            "values": []
          },
          "yaxes": [
            {
              "format": "short",
              "label": null,
              "logBase": 1,
              "max": null,
              "min": null,
              "show": true
            },
            {
              "format": "short",
              "label": null,
              "logBase": 1,
              "max": null,
              "min": null,
              "show": true
            }
          ]
        },
        {
          "aliasColors": {},
          "bars": false,
          "dashLength": 10,
          "dashes": false,
          "datasource": "${DS_PROMETHEUS}",
          "fill": 1,
          "id": 12,
          "legend": {
            "avg": false,
            "current": false,
            "max": false,
            "min": false,
            "show": true,
            "total": false,
            "values": false
          },
          "lines": true,
          "linewidth": 1,
          "links": [],
          "nullPointMode": "null",
          "percentage": false,
          "pointradius": 5,
          "points": false,
          "renderer": "flot",
          "seriesOverrides": [],
          "spaceLength": 10,
          "span": 6,
          "stack": false,
          "steppedLine": false,
          "targets": [
            {
              "expr": "rate(hb_account_GET_requests{job=\"$job\"}[30s])",
              "format": "time_series",
              "intervalFactor": 2,
              "legendFormat": "GET",
              "refId": "A"
            },
            {
              "expr": "rate(hb_account_HEAD_requests{job=\"$job\"}[30s])",
              "format": "time_series",
              "intervalFactor": 2,
              "legendFormat": "HEAD",
              "refId": "B"
            },
            {
              "expr": "rate(hb_account_PUT_requests{job=\"$job\"}[30s])",
              "format": "time_series",
              "intervalFactor": 2,
              "legendFormat": "PUT",
              "refId": "C"
            },
            {
              "expr": "rate(hb_account_requests{job=\"$job\"}[30s])",
              "format": "time_series",
              "intervalFactor": 2,
              "legendFormat": "total",
              "refId": "D"
            }
          ],
          "thresholds": [],
          "timeFrom": null,
          "timeShift": null,
          "title": "Account Requests",
          "tooltip": {
            "shared": true,
            "sort": 0,
            "value_type": "individual"
          },
          "type": "graph",
          "xaxis": {
            "buckets": null,
            "mode": "time",
            "name": null,
            "show": true,
            "values": []
          },
          "yaxes": [
            {
              "format": "short",
              "label": null,
              "logBase": 1,
              "max": null,
              "min": null,
              "show": true
            },
            {
              "format": "short",
              "label": null,
              "logBase": 1,
              "max": null,
              "min": null,
              "show": true
            }
          ]
        }
      ],
      "repeat": null,
      "repeatIteration": null,
      "repeatRowId": null,
      "showTitle": false,
      "title": "Dashboard Row",
      "titleSize": "h6"
    },
    {
      "collapse": false,
      "height": 258,
      "panels": [
        {
          "aliasColors": {},
          "bars": false,
          "dashLength": 10,
          "dashes": false,
          "datasource": "${DS_PROMETHEUS}",
          "fill": 1,
          "id": 13,
          "legend": {
            "avg": false,
            "current": false,
            "max": false,
            "min": false,
            "show": true,
            "total": false,
            "values": false
          },
          "lines": true,
          "linewidth": 1,
          "links": [],
          "nullPointMode": "null",
          "percentage": false,
          "pointradius": 5,
          "points": false,
          "renderer": "flot",
          "seriesOverrides": [],
          "spaceLength": 10,
          "span": 6,
          "stack": false,
          "steppedLine": false,
          "targets": [
            {
              "expr": "rate(hb_container_200_responses{job=\"$job\"}[30s])",
              "format": "time_series",
              "intervalFactor": 2,
              "legendFormat": "200 ",
              "refId": "A"
            },
            {
              "expr": "rate(hb_container_201_responses{job=\"$job\"}[30s])",
              "format": "time_series",
              "intervalFactor": 2,
              "legendFormat": "201",
              "refId": "B"
            },
            {
              "expr": "rate(hb_container_204_responses{job=\"$job\"}[30s])",
              "format": "time_series",
              "intervalFactor": 2,
              "legendFormat": "204",
              "refId": "C"
            }
          ],
          "thresholds": [],
          "timeFrom": null,
          "timeShift": null,
          "title": "Container Response",
          "tooltip": {
            "shared": true,
            "sort": 0,
            "value_type": "individual"
          },
          "type": "graph",
          "xaxis": {
            "buckets": null,
            "mode": "time",
            "name": null,
            "show": true,
            "values": []
          },
          "yaxes": [
            {
              "format": "short",
              "label": null,
              "logBase": 1,
              "max": null,
              "min": null,
              "show": true
            },
            {
              "format": "short",
              "label": null,
              "logBase": 1,
              "max": null,
              "min": null,
              "show": true
            }
          ]
        },
        {
          "aliasColors": {},
          "bars": false,
          "dashLength": 10,
          "dashes": false,
          "datasource": "${DS_PROMETHEUS}",
          "fill": 1,
          "id": 14,
          "legend": {
            "avg": false,
            "current": false,
            "max": false,
            "min": false,
            "show": true,
            "total": false,
            "values": false
          },
          "lines": true,
          "linewidth": 1,
          "links": [],
          "nullPointMode": "null",
          "percentage": false,
          "pointradius": 5,
          "points": false,
          "renderer": "flot",
          "seriesOverrides": [],
          "spaceLength": 10,
          "span": 6,
          "stack": false,
          "steppedLine": false,
          "targets": [
            {
              "expr": "rate(hb_container_GET_requests{job=~\"$job\"}[$interval])",
              "format": "time_series",
              "intervalFactor": 2,
              "legendFormat": "GET",
              "refId": "A"
            },
            {
              "expr": "rate(hb_container_HEAD_requests{job=~\"$job\"}[$interval])",
              "format": "time_series",
              "intervalFactor": 2,
              "legendFormat": "HEAD",
              "refId": "B"
            },
            {
              "expr": "rate(hb_container_PUT_requests{job=~\"$job\"}[$interval])",
              "format": "time_series",
              "intervalFactor": 2,
              "legendFormat": "PUT",
              "refId": "C"
            },
            {
              "expr": "rate(hb_container_requests{job=~\"$job\"}[$interval])",
              "format": "time_series",
              "intervalFactor": 2,
              "legendFormat": "total",
              "refId": "D"
            }
          ],
          "thresholds": [],
          "timeFrom": null,
          "timeShift": null,
          "title": "Container Request",
          "tooltip": {
            "shared": true,
            "sort": 0,
            "value_type": "individual"
          },
          "type": "graph",
          "xaxis": {
            "buckets": null,
            "mode": "time",
            "name": null,
            "show": true,
            "values": []
          },
          "yaxes": [
            {
              "format": "short",
              "label": null,
              "logBase": 1,
              "max": null,
              "min": null,
              "show": true
            },
            {
              "format": "short",
              "label": null,
              "logBase": 1,
              "max": null,
              "min": null,
              "show": true
            }
          ]
        }
      ],
      "repeat": null,
      "repeatIteration": null,
      "repeatRowId": null,
      "showTitle": false,
      "title": "Dashboard Row",
      "titleSize": "h6"
    },
    {
      "collapse": false,
      "height": 222,
      "panels": [
        {
          "aliasColors": {},
          "bars": false,
          "dashLength": 10,
          "dashes": false,
          "datasource": "${DS_PROMETHEUS}",
          "fill": 1,
          "id": 15,
          "legend": {
            "avg": false,
            "current": false,
            "max": false,
            "min": false,
            "show": true,
            "total": false,
            "values": false
          },
          "lines": true,
          "linewidth": 1,
          "links": [],
          "nullPointMode": "null",
          "percentage": false,
          "pointradius": 5,
          "points": false,
          "renderer": "flot",
          "seriesOverrides": [],
          "spaceLength": 10,
          "span": 6,
          "stack": false,
          "steppedLine": false,
          "targets": [
            {
              "expr": "rate(hb_object_200_responses{job=\"$job\"}[30s])",
              "format": "time_series",
              "intervalFactor": 2,
              "legendFormat": "200",
              "refId": "A"
            },
            {
              "expr": "rate(hb_object_201_responses{job=\"$job\"}[30s])",
              "format": "time_series",
              "intervalFactor": 2,
              "legendFormat": "201",
              "refId": "B"
            },
            {
              "expr": "rate(hb_object_400_responses{job=\"$job\"}[30s])",
              "format": "time_series",
              "intervalFactor": 2,
              "legendFormat": "400",
              "refId": "C"
            },
            {
              "expr": "rate(hb_object_500_responses{job=\"$job\"}[30s])",
              "format": "time_series",
              "intervalFactor": 2,
              "legendFormat": "500",
              "refId": "D"
            },
            {
              "expr": "rate(hb_object_507_responses{job=\"$job\"}[30s])",
              "format": "time_series",
              "intervalFactor": 2,
              "legendFormat": "507",
              "refId": "E"
            }
          ],
          "thresholds": [],
          "timeFrom": null,
          "timeShift": null,
          "title": "Object Responses",
          "tooltip": {
            "shared": true,
            "sort": 0,
            "value_type": "individual"
          },
          "type": "graph",
          "xaxis": {
            "buckets": null,
            "mode": "time",
            "name": null,
            "show": true,
            "values": []
          },
          "yaxes": [
            {
              "format": "short",
              "label": null,
              "logBase": 1,
              "max": null,
              "min": null,
              "show": true
            },
            {
              "format": "short",
              "label": null,
              "logBase": 1,
              "max": null,
              "min": null,
              "show": true
            }
          ]
        },
        {
          "aliasColors": {},
          "bars": false,
          "dashLength": 10,
          "dashes": false,
          "datasource": "${DS_PROMETHEUS}",
          "fill": 1,
          "id": 16,
          "legend": {
            "avg": false,
            "current": false,
            "max": false,
            "min": false,
            "show": true,
            "total": false,
            "values": false
          },
          "lines": true,
          "linewidth": 1,
          "links": [],
          "nullPointMode": "null",
          "percentage": false,
          "pointradius": 5,
          "points": false,
          "renderer": "flot",
          "seriesOverrides": [],
          "spaceLength": 10,
          "span": 6,
          "stack": false,
          "steppedLine": false,
          "targets": [
            {
              "expr": "rate(hb_object_GET_requests{job=\"$job\"}[30s])",
              "format": "time_series",
              "intervalFactor": 2,
              "legendFormat": "GET",
              "refId": "A"
            },
            {
              "expr": "rate(hb_object_PUT_requests{job=\"$job\"}[30s])",
              "format": "time_series",
              "intervalFactor": 2,
              "legendFormat": "PUT",
              "refId": "B"
            },
            {
              "expr": "rate(hb_object_requests{job=\"$job\"}[30s])",
              "format": "time_series",
              "intervalFactor": 2,
              "legendFormat": "total",
              "refId": "C"
            }
          ],
          "thresholds": [],
          "timeFrom": null,
          "timeShift": null,
          "title": "Object Request",
          "tooltip": {
            "shared": true,
            "sort": 0,
            "value_type": "individual"
          },
          "type": "graph",
          "xaxis": {
            "buckets": null,
            "mode": "time",
            "name": null,
            "show": true,
            "values": []
          },
          "yaxes": [
            {
              "format": "short",
              "label": null,
              "logBase": 1,
              "max": null,
              "min": null,
              "show": true
            },
            {
              "format": "short",
              "label": null,
              "logBase": 1,
              "max": null,
              "min": null,
              "show": true
            }
          ]
        }
      ],
      "repeat": null,
      "repeatIteration": null,
      "repeatRowId": null,
      "showTitle": false,
      "title": "Dashboard Row",
      "titleSize": "h6"
    }
  ],
  "schemaVersion": 14,
  "style": "dark",
  "tags": [],
  "templating": {
    "list": [
      {
        "allValue": null,
        "current": {},
        "datasource": "${DS_PROMETHEUS}",
        "hide": 0,
        "includeAll": true,
        "label": null,
        "multi": true,
        "name": "job",
        "options": [],
        "query": "label_values(go_goroutines, job)",
        "refresh": 2,
        "regex": "",
        "sort": 0,
        "tagValuesQuery": "",
        "tags": [],
        "tagsQuery": "",
        "type": "query",
        "useTags": false
      },
      {
        "auto": false,
        "auto_count": 30,
        "auto_min": "10s",
        "current": {
          "text": "1m",
          "value": "1m"
        },
        "hide": 0,
        "label": null,
        "name": "interval",
        "options": [
          {
            "selected": false,
            "text": "15s",
            "value": "15s"
          },
          {
            "selected": false,
            "text": "30s",
            "value": "30s"
          },
          {
            "selected": false,
            "text": "45s",
            "value": "45s"
          },
          {
            "selected": true,
            "text": "1m",
            "value": "1m"
          },
          {
            "selected": false,
            "text": "10m",
            "value": "10m"
          },
          {
            "selected": false,
            "text": "30m",
            "value": "30m"
          },
          {
            "selected": false,
            "text": "1h",
            "value": "1h"
          },
          {
            "selected": false,
            "text": "6h",
            "value": "6h"
          },
          {
            "selected": false,
            "text": "12h",
            "value": "12h"
          },
          {
            "selected": false,
            "text": "1d",
            "value": "1d"
          },
          {
            "selected": false,
            "text": "7d",
            "value": "7d"
          },
          {
            "selected": false,
            "text": "14d",
            "value": "14d"
          },
          {
            "selected": false,
            "text": "30d",
            "value": "30d"
          }
        ],
        "query": "15s,30s,45s,1m,10m,30m,1h,6h,12h,1d,7d,14d,30d",
        "refresh": 2,
        "type": "interval"
      }
    ]
  },
  "time": {
    "from": "now-15m",
    "to": "now"
  },
  "timepicker": {
    "refresh_intervals": [
      "5s",
      "10s",
      "30s",
      "1m",
      "5m",
      "15m",
      "30m",
      "1h",
      "2h",
      "1d"
    ],
    "time_options": [
      "5m",
      "15m",
      "1h",
      "6h",
      "12h",
      "24h",
      "2d",
      "7d",
      "30d"
    ]
  },
  "timezone": "browser",
  "title": "Hummingbird",
  "version": 11
}